autotune/__init__.py
autotune/spec.py
autotune/tuner.py
autotune-0.0.3.dist-info/DESCRIPTION.rst
autotune-0.0.3.dist-info/METADATA
autotune-0.0.3.dist-info/RECORD
autotune-0.0.3.dist-info/WHEEL
autotune-0.0.3.dist-info/entry_points.txt
autotune-0.0.3.dist-info/metadata.json
autotune-0.0.3.dist-info/top_level.txt
